franklab_msdrift/__init__.py
franklab_msdrift/drift.mp
franklab_msdrift/drift.py
franklab_msdrift/p_anneal_segments.py
franklab_msdrift/p_concatenate_firings.py
franklab_msdrift/p_extract_subfirings.py
franklab_msdrift/p_handle_drift_in_segment.py
franklab_msdrift/p_join_segments.py
franklab_msdrift/p_reptrack.py
franklab_msdrift/timeserieschunkreader.py
franklab_msdrift-0.1.9.dev0.dist-info/METADATA
franklab_msdrift-0.1.9.dev0.dist-info/WHEEL
franklab_msdrift-0.1.9.dev0.dist-info/top_level.txt
franklab_msdrift-0.1.9.dev0.dist-info/RECORD
